butter/__init__.py
butter/mas/__init__.py
butter/mas/api.py
butter/mas/environment.py
butter/mas/clients/__init__.py
butter/mas/clients/client.py
butter/mas/clients/client_factory.py
butter/mas/clients/client_http.py
butter/mas/clients/client_tcp.py
butter/mas/clients/client_udp.py
butter/mas/interfaces/__init__.py
butter/mas/interfaces/types.py
butter/mas/packets/__init__.py
butter/mas/packets/packet.py
butter/mas/packets/packet_builder.py
butter/mas/packets/packet_factory.py
butter/mas/packets/packet_http.py
butter/mas/packets/packet_tcp.py
butter/mas/packets/packet_udp.py
butter/mas/tests/__init__.py
butter/mas/tests/api_test.py
butter/mas/tests/clients/__init__.py
butter/mas/tests/clients/client_http_test.py
butter/mas/tests/clients/client_tcp_test.py
butter/mas/tests/clients/client_test.py
butter/mas/tests/clients/client_udp_test.py
butter/mas/tests/packets/__init__.py
butter/mas/tests/packets/packet_builder_test.py
butter/mas/tests/packets/packet_http_test.py
butter/mas/tests/packets/packet_tcp_test.py
butter/mas/tests/packets/packet_udp_test.py
butter/mas/tests/utils/__init__.py
butter/mas/tests/utils/version_validations_test.py
butter/mas/utils/__init__.py
butter/mas/utils/general_utils.py
butter/mas/utils/response_parser.py
butter/mas/utils/version_utils.py
butter.mas_api-2.1.1.dist-info/LICENSE
butter.mas_api-2.1.1.dist-info/METADATA
butter.mas_api-2.1.1.dist-info/NOTICE
butter.mas_api-2.1.1.dist-info/WHEEL
butter.mas_api-2.1.1.dist-info/top_level.txt
butter.mas_api-2.1.1.dist-info/RECORD
