Metadata-Version: 2.1
Name: butter.mas-api
Version: 2.1.1
Summary: Python Client API for Butter MAS platform
Home-page: https://butterrobotics.com
Author: Benny Megidish
Author-email: bennymegk@gmail.com
License: Apache-2.0
Project-URL: Documentation, https://butterrobotics.com/#/library/documentation/mas_os_python_api
Project-URL: Source, https://github.com/bennymeg/Butter.MAS.PythonAPI
Project-URL: Tracker, https://github.com/bennymeg/Butter.MAS.PythonAPI/issues
Platform: UNKNOWN
Classifier: Development Status :: 5 - Production/Stable
Classifier: Intended Audience :: Developers
Classifier: Intended Audience :: Science/Research
Classifier: Intended Audience :: Education
Classifier: Intended Audience :: End Users/Desktop
Classifier: Operating System :: OS Independent
Classifier: Topic :: Scientific/Engineering :: Human Machine Interfaces
Classifier: License :: OSI Approved :: Apache Software License
Classifier: Programming Language :: Python :: 3
Requires-Dist: requests
Requires-Dist: packaging
